Metadata-Version: 2.1
Name: kivy-garden.xcamera
Version: 2020.613
Summary: Real time Barcode and QR Code scanner Edit
Home-page: https://github.com/kivy-garden/xcamera
Author: Antonio Cuni
License: UNKNOWN
Platform: UNKNOWN
Requires-Python: >=3
